midjpy/midj.py
midjpy-1.0.4.dist-info/METADATA
midjpy-1.0.4.dist-info/WHEEL
midjpy-1.0.4.dist-info/top_level.txt
midjpy-1.0.4.dist-info/RECORD
